__init__.py
TYC_ENGINE/__init__.py
TYC_ENGINE/cli.py
TYC_ENGINE/project.py
TYC_ENGINE/assets/__init__.py
TYC_ENGINE/assets/lib_assets/__init__.py
TYC_ENGINE/assets/lib_assets/color/b.py
TYC_ENGINE/assets/lib_assets/color/basic.py
TYC_ENGINE/assets/lib_assets/color/g.py
TYC_ENGINE/assets/lib_assets/color/r.py
TYC_ENGINE/assets/lib_assets/py_assets/__init__.py
TYC_ENGINE/assets/lib_assets/py_assets/__main__.py
TYC_ENGINE/assets/lib_assets/py_assets/core.py
TYC_ENGINE/assets/lib_assets/py_assets/engine.py
TYC_ENGINE/assets/lib_assets/py_assets/loader.py
TYC_ENGINE/templates/project/manage.py
TYC_ENGINE/templates/project/App/__init__.py
TYC_ENGINE/templates/project/App/main.py
TYC_ENGINE/templates/project/App/setting.py
tyc_engine-0.6.63.dist-info/licenses/LICENSE
tyc_engine-0.6.63.dist-info/METADATA
tyc_engine-0.6.63.dist-info/WHEEL
tyc_engine-0.6.63.dist-info/entry_points.txt
tyc_engine-0.6.63.dist-info/top_level.txt
tyc_engine-0.6.63.dist-info/RECORD
