Metadata-Version: 2.4
Name: tyc-engine
Version: 0.6.63
Summary: Lоl
Author-email: TYC <dema29992@gmail.com>
License-File: LICENSE
Requires-Dist: pygame
Requires-Dist: rich
Dynamic: license-file
